django_sandwich_tag-0.2.0.dist-info/licenses/LICENSE
sandwich_tag/__init__.py
sandwich_tag/apps.py
sandwich_tag/helpers.py
sandwich_tag/templatetags/__init__.py
sandwich_tag/templatetags/sandwich.py
django_sandwich_tag-0.2.0.dist-info/METADATA
django_sandwich_tag-0.2.0.dist-info/WHEEL
django_sandwich_tag-0.2.0.dist-info/top_level.txt
django_sandwich_tag-0.2.0.dist-info/RECORD
