Metadata-Version: 2.4
Name: django-sandwich-tag
Version: 0.2.0
Summary: A django template tag that simplifies nested templates.
Author-email: Jacob Tumak <jtumak.dev@gmail.com>
License: MIT License
Project-URL: Homepage, https://github.com/jacobtumak/django-sandwich-tag
Project-URL: Repository, https://github.com/jacobtumak/django-sandwich-tag
Keywords: sandwich,sandwich_tag,django-sandwich-tag
Classifier: Development Status :: 2 - Pre-Alpha
Classifier: License :: OSI Approved :: MIT License
Classifier: Intended Audience :: Developers
Classifier: Natural Language :: English
Classifier: Programming Language :: Python :: 3
Classifier: Framework :: Django
Requires-Python: <4.0,>=3.10
License-File: LICENSE
Requires-Dist: django<6.0,>=4.2
Provides-Extra: test
Requires-Dist: pytest; extra == "test"
Requires-Dist: pytest-django; extra == "test"
Requires-Dist: pytest-cov; extra == "test"
Requires-Dist: pytest-sugar; extra == "test"
Provides-Extra: utils
Requires-Dist: tox; extra == "utils"
Requires-Dist: invoke; extra == "utils"
Requires-Dist: bumpver; extra == "utils"
Requires-Dist: pip-tools; extra == "utils"
Provides-Extra: format
Requires-Dist: black; extra == "format"
Requires-Dist: isort; extra == "format"
Provides-Extra: lint
Requires-Dist: flake8; extra == "lint"
Requires-Dist: flake8-bugbear; extra == "lint"
Provides-Extra: build
Requires-Dist: build; extra == "build"
Requires-Dist: twine; extra == "build"
Dynamic: license-file
